DEBUG.md
LICENSE
LOG.md
MANIFEST.in
NEWS.md
README.md
TODO.md
code-style.md
requirements.txt
setup.cfg
setup.py
docs/source/conf.py
docs/source/index.rst
docs/source/getting_started/index.rst
docs/source/getting_started/install.md
docs/source/reference/index.rst
docs/source/reference/iterutils.rst
docs/source/reference/mconfbase.rst
docs/source/reference/msmg.rst
docs/source/reference/sysinfo.rst
docs/source/reference/api/trainer.MessageManager.band_trainName.rst
docs/source/reference/api/trainer.MessageManager.describe.rst
docs/source/reference/api/trainer.MessageManager.free_trainName.rst
docs/source/reference/api/trainer.MessageManager.rst
docs/source/reference/api/trainer.ModelConfigBase.to_dict.rst
docs/source/reference/api/trainer.MqConn.close.rst
docs/source/reference/api/trainer.MqConn.delete_queue.rst
docs/source/reference/api/trainer.MqConn.pull.rst
docs/source/reference/api/trainer.MqConn.push.rst
docs/source/reference/api/trainer.MqConn.rst
docs/source/reference/api/trainer.Serializer.rst
docs/source/reference/api/trainer.Serializer.serialize.rst
docs/source/reference/api/trainer.Serializer.serialize_inv.rst
docs/source/reference/api/trainer.is_continue_in_batchState.rst
docs/source/reference/api/trainer.is_continue_in_epochState.rst
docs/source/reference/api/trainer.run_sysinfo_subprocess.rst
docs/source/user_guide/index.rst
docs/source/user_guide/projectstruct.md
docs/source/user_guide/start.md
docs/source/user_guide/startapp.md
nginx/sites-enabled/trainer_project.conf
scripts/build_require.py
scripts/gen_docs.py
scripts/package.py
test/test_linemodel.py
trainer/__init__.py
trainer/version.py
trainer/backend/__init__.py
trainer/backend/apptrainer.py
trainer/backend/loger.py
trainer/backend/app/basemodel.py
trainer/backend/app/test.py
trainer/backend/app/batchstate/model.py
trainer/backend/app/batchstate/view.py
trainer/backend/app/datasetinfo/dynamic/model.py
trainer/backend/app/datasetinfo/dynamic/view.py
trainer_xy.egg-info/PKG-INFO
trainer_xy.egg-info/SOURCES.txt
trainer_xy.egg-info/dependency_links.txt
trainer_xy.egg-info/not-zip-safe
trainer_xy.egg-info/requires.txt
trainer_xy.egg-info/top_level.txt