Metadata-Version: 2.1
Name: trainer-xy
Version: 0.0.1
Summary: trainer dashboard
Home-page: https://github.com/songyanyi/Trainer
Author: syy
Author-email: 1121225022@qq.com
Maintainer: syy
Maintainer-email: 1121225022@qq.com
License: BSD
Keywords: trainer,train,machine learning,deep learning
Platform: UNKNOWN
Classifier: Development Status :: 2 - Pre-Alpha
Classifier: Environment :: Console
Classifier: Natural Language :: Chinese (Simplified)
Classifier: Natural Language :: English
Classifier: Operating System :: OS Independent
Classifier: Intended Audience :: Science/Research
Classifier: Programming Language :: Python :: 3 :: Only
Classifier: Programming Language :: Python :: 3.5
Classifier: Programming Language :: Python :: 3.6
Classifier: Programming Language :: Python :: 3.7
Classifier: Topic :: Scientific/Engineering
Classifier: Topic :: Scientific/Engineering :: Artificial Intelligence
Classifier: Topic :: Scientific/Engineering :: Image Recognition
Requires-Python: >=3.5
